[
  {
    "id": "1",
    "subject": "CIT 366 assignment 1",
    "msgText": "The grades for this assignment have been posted.",
    "senderId": "7"
  },
  {
    "id": "2",
    "subject": "CIT 366 assignment 3",
    "msgText": "When is assignment 3 due?",
    "senderId": "13"
  },
  {
    "id": "3",
    "subject": "CIT 366 assignment 3 due date",
    "msgText": "Assignment 3 is due on Saturday at 11:30 PM.",
    "senderId": "7"
  },
  {
    "id": "4",
    "subject": "Assignment 3 help",
    "msgText": "Can I meet with you sometime? I need help with assignment 3.",
    "senderId": "3"
  },
  {
    "id": "5",
    "subject": "Assignment 3 help",
    "msgText": "I can meet with you today at 4:00 PM in my office.",
    "senderId": "7"
  },
  {
    "id": "6",
    "subject": "Ayuda!!! I need help with this",
    "msgText": "I'm stuck with a bug.",
    "senderId": "14"
  }
]